ego_ib/__init__.py
ego_ib/ib_gateway.cpython-310-x86_64-linux-gnu.so
ego_addons-2024.129.dist-info/LICENSE
ego_addons-2024.129.dist-info/METADATA
ego_addons-2024.129.dist-info/WHEEL
ego_addons-2024.129.dist-info/top_level.txt
ego_addons-2024.129.dist-info/RECORD
