Metadata-Version: 2.1
Name: ego_addons
Version: 2024.129
Summary: Define your trading style.
Home-page: https://pypi.org/project/egopy
Author: EGOPY
License: BSD 3-Clause License
Classifier: Operating System :: POSIX :: Linux
Classifier: Programming Language :: Python :: 3
Classifier: Programming Language :: C
Classifier: Topic :: Office/Business :: Financial
Classifier: Topic :: Scientific/Engineering :: Mathematics
Classifier: License :: OSI Approved :: BSD License
Classifier: Natural Language :: Chinese (Simplified)
Requires-Python: <3.11,>=3.10
License-File: LICENSE
